py_ioc/__init__.py
py_ioc/container.py
py_ioc-0.1.0.dist-info/DESCRIPTION.rst
py_ioc-0.1.0.dist-info/METADATA
py_ioc-0.1.0.dist-info/RECORD
py_ioc-0.1.0.dist-info/WHEEL
py_ioc-0.1.0.dist-info/metadata.json
py_ioc-0.1.0.dist-info/top_level.txt
