Metadata-Version: 2.0
Name: py-ioc
Version: 0.1.0
Summary: Inversion of Control Container for Automatic Dependency Injection
Home-page: https://github.com/emilniklas/py_ioc
Author: Emil Person
Author-email: emil.n.persson@gmail.com
License: UNKNOWN
Download-URL: https://github.com/emilniklas/py_ioc/tarball/0.1.0
Keywords: ioc,di,dependency injection,inversion of control
Platform: UNKNOWN
Classifier: Programming Language :: Python :: 3
Classifier: Programming Language :: Python :: 3.3
Classifier: Programming Language :: Python :: 3.4
Classifier: Programming Language :: Python :: 3.5
Classifier: Programming Language :: Python :: 3.6
